ngawari/__init__.py
ngawari/fIO.py
ngawari/ftk.py
ngawari/vtkfilters.py
ngawari/tests/context.py
ngawari/tests/run_tests_fIO.py
ngawari/tests/run_tests_ftk.py
ngawari/tests/run_tests_vtkfilters.py
ngawari-0.1.17.dist-info/METADATA
ngawari-0.1.17.dist-info/WHEEL
ngawari-0.1.17.dist-info/licenses/LICENSE
ngawari-0.1.17.dist-info/RECORD
